[
  {
    "model": "authapp.shopuser",
    "pk": 1,
    "fields": {
      "password": "pbkdf2_sha256$150000$Fk1q2LwZerNM$Ee+s8B7xqQb2D1Hdh4nzpsssCzsHRQFaoFR02xmDtcg=",
      "last_login": "2020-10-12T15:02:00.808Z",
      "is_superuser": true,
      "username": "nubobap",
      "first_name": "",
      "last_name": "",
      "email": "nubobap2015@yandex.ru",
      "is_staff": true,
      "is_active": true,
      "date_joined": "2020-10-09T09:48:12.932Z",
      "avatar": "",
      "age": 39,
      "groups": [],
      "user_permissions": []
    }
  },
  {
    "model": "authapp.shopuser",
    "pk": 2,
    "fields": {
      "password": "pbkdf2_sha256$150000$Fk1q2LwZerNM$Ee+s8B7xqQb2D1Hdh4nzpsssCzsHRQFaoFR02xmDtcg=",
      "last_login": null,
      "is_superuser": true,
      "username": "admin",
      "first_name": "\u0421\u0435\u0440\u0433\u0435\u0439",
      "last_name": "\u0421\u0430\u043d\u0442\u0438\u043a\u043e\u0432",
      "email": "ww@ya.ru",
      "is_staff": true,
      "is_active": true,
      "date_joined": "2020-10-12T14:38:14Z",
      "avatar": "",
      "age": 33,
      "groups": [],
      "user_permissions": []
    }
  }
]